jupyter_existing_provisioner/__init__.py
jupyter_existing_provisioner/existing.py
jupyter_existing_provisioner-0.1.1.dist-info/LICENSE.md
jupyter_existing_provisioner-0.1.1.dist-info/METADATA
jupyter_existing_provisioner-0.1.1.dist-info/WHEEL
jupyter_existing_provisioner-0.1.1.dist-info/entry_points.txt
jupyter_existing_provisioner-0.1.1.dist-info/top_level.txt
jupyter_existing_provisioner-0.1.1.dist-info/RECORD
