Metadata-Version: 2.1
Name: jupyter-existing-provisioner
Version: 0.1.1
Summary: Connect to the last started kernel or by connection file.
License: UNKNOWN
Project-URL: Source, https://github.com/sv99/ida-jupyter
Project-URL: Tracker, https://github.com/sv99/ida-jupyter/issues
Platform: UNKNOWN
Classifier: Programming Language :: Python :: 3
Classifier: License :: OSI Approved :: MIT License
Classifier: Operating System :: Microsoft :: Windows
License-File: LICENSE.md
Requires-Dist: jupyter-client (>=7.0.0)
